{
  "scene": "FloorPlan1",
  "num_relations": 41,
  "inverse_relation_map": {
    "in": "contains",
    "on": "supports",
    "left_of": "right_of",
    "above": "below"
  },
  "relations": [
    {
      "subject_id": "Fork|+00.95|+00.77|-02.37",
      "subject_type": "Fork",
      "relation": "near",
      "object_id": "Spoon|+00.98|+00.77|-02.29",
      "object_type": "Spoon",
      "relation_family": "geometric",
      "candidate_for_text": true,
      "verbalizable": true,
      "evidence": {
        "rule": "horizontal_distance",
        "horizontal_distance": 0.08524565008111029,
        "threshold": 0.5
      }
    },
    {
      "subject_id": "Spoon|+00.98|+00.77|-02.29",
      "subject_type": "Spoon",
      "relation": "near",
      "object_id": "Drawer|+00.95|+00.83|-02.20",
      "object_type": "Drawer",
      "relation_family": "geometric",
      "candidate_for_text": true,
      "verbalizable": true,
      "evidence": {
        "rule": "horizontal_distance",
        "horizontal_distance": 0.09583610855631763,
        "threshold": 0.5
      }
    },
    {
      "subject_id": "Pot|-01.22|+00.90|-02.36",
      "subject_type": "Pot",
      "relation": "near",
      "object_id": "Cabinet|-01.18|+00.50|-02.20",
      "object_type": "Cabinet",
      "relation_family": "geometric",
      "candidate_for_text": true,
      "verbalizable": true,
      "evidence": {
        "rule": "horizontal_distance",
        "horizontal_distance": 0.16080143443842781,
        "threshold": 0.5
      }
    },
    {
      "subject_id": "Pot|-01.22|+00.90|-02.36",
      "subject_type": "Pot",
      "relation": "near",
      "object_id": "WineBottle|-01.00|+01.65|-02.58",
      "object_type": "WineBottle",
      "relation_family": "geometric",
      "candidate_for_text": true,
      "verbalizable": true,
      "evidence": {
        "rule": "horizontal_distance",
        "horizontal_distance": 0.3153235595581186,
        "threshold": 0.5
      }
    },
    {
      "subject_id": "Pot|-01.22|+00.90|-02.36",
      "subject_type": "Pot",
      "relation": "near",
      "object_id": "Cabinet|-01.69|+02.02|-02.46",
      "object_type": "Cabinet",
      "relation_family": "geometric",
      "candidate_for_text": true,
      "verbalizable": true,
      "evidence": {
        "rule": "horizontal_distance",
        "horizontal_distance": 0.47810618964409024,
        "threshold": 0.5
      }
    },
    {
      "subject_id": "WineBottle|-01.00|+01.65|-02.58",
      "subject_type": "WineBottle",
      "relation": "near",
      "object_id": "Cabinet|-01.18|+00.50|-02.20",
      "object_type": "Cabinet",
      "relation_family": "geometric",
      "candidate_for_text": true,
      "verbalizable": true,
      "evidence": {
        "rule": "horizontal_distance",
        "horizontal_distance": 0.42351575982667033,
        "threshold": 0.5
      }
    },
    {
      "subject_id": "Fork|+00.95|+00.77|-02.37",
      "subject_type": "Fork",
      "relation": "in",
      "object_id": "Drawer|+00.95|+00.83|-02.20",
      "object_type": "Drawer",
      "relation_family": "topological",
      "candidate_for_text": true,
      "verbalizable": true,
      "evidence": {}
    },
    {
      "subject_id": "Spoon|+00.98|+00.77|-02.29",
      "subject_type": "Spoon",
      "relation": "in",
      "object_id": "Drawer|+00.95|+00.83|-02.20",
      "object_type": "Drawer",
      "relation_family": "topological",
      "candidate_for_text": true,
      "verbalizable": true,
      "evidence": {}
    },
    {
      "subject_id": "Pot|-01.22|+00.90|-02.36",
      "subject_type": "Pot",
      "relation": "on",
      "object_id": "CounterTop|-01.87|+00.95|-01.21",
      "object_type": "CounterTop",
      "relation_family": "topological",
      "candidate_for_text": true,
      "verbalizable": true,
      "evidence": {}
    },
    {
      "subject_id": "Drawer|+00.95|+00.56|-02.20",
      "subject_type": "Drawer",
      "relation": "below",
      "object_id": "Fork|+00.95|+00.77|-02.37",
      "object_type": "Fork",
      "relation_family": "geometric",
      "candidate_for_text": true,
      "verbalizable": true,
      "evidence": {
        "source": "inverse_relation",
        "forward_relation": "above",
        "forward_evidence": {
          "rule": "vertical_clearance_with_xz_overlap",
          "y_clearance": 0.15569865703582764,
          "x_overlap": 0.03355133533477783,
          "z_overlap": 0.24777793884277344,
          "y_margin": 0.03
        }
      },
      "is_inverse_relation": true,
      "derived_from_relation": "above"
    },
    {
      "subject_id": "Fork|+00.95|+00.77|-02.37",
      "subject_type": "Fork",
      "relation": "above",
      "object_id": "Drawer|+00.95|+00.22|-02.20",
      "object_type": "Drawer",
      "relation_family": "geometric",
      "candidate_for_text": true,
      "verbalizable": true,
      "evidence": {
        "rule": "vertical_clearance_with_xz_overlap",
        "y_clearance": 0.4946986436843872,
        "x_overlap": 0.03355133533477783,
        "z_overlap": 0.24777793884277344,
        "y_margin": 0.03
      }
    },
    {
      "subject_id": "Spoon|+00.98|+00.77|-02.29",
      "subject_type": "Spoon",
      "relation": "above",
      "object_id": "Drawer|+00.95|+00.56|-02.20",
      "object_type": "Drawer",
      "relation_family": "geometric",
      "candidate_for_text": true,
      "verbalizable": true,
      "evidence": {
        "rule": "vertical_clearance_with_xz_overlap",
        "y_clearance": 0.15582990646362305,
        "x_overlap": 0.0409846305847168,
        "z_overlap": 0.20708036422729492,
        "y_margin": 0.03
      }
    },
    {
      "subject_id": "Spoon|+00.98|+00.77|-02.29",
      "subject_type": "Spoon",
      "relation": "above",
      "object_id": "Drawer|+00.95|+00.22|-02.20",
      "object_type": "Drawer",
      "relation_family": "geometric",
      "candidate_for_text": true,
      "verbalizable": true,
      "evidence": {
        "rule": "vertical_clearance_with_xz_overlap",
        "y_clearance": 0.4948298931121826,
        "x_overlap": 0.0409846305847168,
        "z_overlap": 0.20708036422729492,
        "y_margin": 0.03
      }
    },
    {
      "subject_id": "Fork|+00.95|+00.77|-02.37",
      "subject_type": "Fork",
      "relation": "right_of",
      "object_id": "Pot|-01.22|+00.90|-02.36",
      "object_type": "Pot",
      "relation_family": "geometric",
      "candidate_for_text": true,
      "verbalizable": true,
      "evidence": {
        "source": "inverse_relation",
        "forward_relation": "left_of",
        "forward_evidence": {
          "rule": "x_separation",
          "x_gap": 2.0142329335212708,
          "margin": 0.05
        }
      },
      "is_inverse_relation": true,
      "derived_from_relation": "left_of"
    },
    {
      "subject_id": "Pot|-01.22|+00.90|-02.36",
      "subject_type": "Pot",
      "relation": "left_of",
      "object_id": "Drawer|+00.95|+00.83|-02.20",
      "object_type": "Drawer",
      "relation_family": "geometric",
      "candidate_for_text": true,
      "verbalizable": true,
      "evidence": {
        "rule": "x_separation",
        "x_gap": 1.791880488395691,
        "margin": 0.05
      }
    },
    {
      "subject_id": "Spoon|+00.98|+00.77|-02.29",
      "subject_type": "Spoon",
      "relation": "right_of",
      "object_id": "Pot|-01.22|+00.90|-02.36",
      "object_type": "Pot",
      "relation_family": "geometric",
      "candidate_for_text": true,
      "verbalizable": true,
      "evidence": {
        "source": "inverse_relation",
        "forward_relation": "left_of",
        "forward_evidence": {
          "rule": "x_separation",
          "x_gap": 2.044351816177368,
          "margin": 0.05
        }
      },
      "is_inverse_relation": true,
      "derived_from_relation": "left_of"
    },
    {
      "subject_id": "Pot|-01.22|+00.90|-02.36",
      "subject_type": "Pot",
      "relation": "left_of",
      "object_id": "Drawer|+00.95|+00.56|-02.20",
      "object_type": "Drawer",
      "relation_family": "geometric",
      "candidate_for_text": true,
      "verbalizable": true,
      "evidence": {
        "rule": "x_separation",
        "x_gap": 1.791880488395691,
        "margin": 0.05
      }
    },
    {
      "subject_id": "Pot|-01.22|+00.90|-02.36",
      "subject_type": "Pot",
      "relation": "left_of",
      "object_id": "Drawer|+00.95|+00.22|-02.20",
      "object_type": "Drawer",
      "relation_family": "geometric",
      "candidate_for_text": true,
      "verbalizable": true,
      "evidence": {
        "rule": "x_separation",
        "x_gap": 1.791880488395691,
        "margin": 0.05
      }
    },
    {
      "subject_id": "CounterTop|-01.87|+00.95|-01.21",
      "subject_type": "CounterTop",
      "relation": "left_of",
      "object_id": "Fork|+00.95|+00.77|-02.37",
      "object_type": "Fork",
      "relation_family": "geometric",
      "candidate_for_text": true,
      "verbalizable": true,
      "evidence": {
        "rule": "x_separation",
        "x_gap": 1.6325910687446594,
        "margin": 0.05
      }
    },
    {
      "subject_id": "Spoon|+00.98|+00.77|-02.29",
      "subject_type": "Spoon",
      "relation": "right_of",
      "object_id": "CounterTop|-01.87|+00.95|-01.21",
      "object_type": "CounterTop",
      "relation_family": "geometric",
      "candidate_for_text": true,
      "verbalizable": true,
      "evidence": {
        "source": "inverse_relation",
        "forward_relation": "left_of",
        "forward_evidence": {
          "rule": "x_separation",
          "x_gap": 1.6627099514007568,
          "margin": 0.05
        }
      },
      "is_inverse_relation": true,
      "derived_from_relation": "left_of"
    },
    {
      "subject_id": "Fork|+00.95|+00.77|-02.37",
      "subject_type": "Fork",
      "relation": "right_of",
      "object_id": "Cabinet|-01.18|+00.50|-02.20",
      "object_type": "Cabinet",
      "relation_family": "geometric",
      "candidate_for_text": true,
      "verbalizable": true,
      "evidence": {
        "source": "inverse_relation",
        "forward_relation": "left_of",
        "forward_evidence": {
          "rule": "x_separation",
          "x_gap": 1.6475905776023865,
          "margin": 0.05
        }
      },
      "is_inverse_relation": true,
      "derived_from_relation": "left_of"
    },
    {
      "subject_id": "Spoon|+00.98|+00.77|-02.29",
      "subject_type": "Spoon",
      "relation": "right_of",
      "object_id": "Cabinet|-01.18|+00.50|-02.20",
      "object_type": "Cabinet",
      "relation_family": "geometric",
      "candidate_for_text": true,
      "verbalizable": true,
      "evidence": {
        "source": "inverse_relation",
        "forward_relation": "left_of",
        "forward_evidence": {
          "rule": "x_separation",
          "x_gap": 1.6777094602584839,
          "margin": 0.05
        }
      },
      "is_inverse_relation": true,
      "derived_from_relation": "left_of"
    },
    {
      "subject_id": "Fork|+00.95|+00.77|-02.37",
      "subject_type": "Fork",
      "relation": "right_of",
      "object_id": "WineBottle|-01.00|+01.65|-02.58",
      "object_type": "WineBottle",
      "relation_family": "geometric",
      "candidate_for_text": true,
      "verbalizable": true,
      "evidence": {
        "source": "inverse_relation",
        "forward_relation": "left_of",
        "forward_evidence": {
          "rule": "x_separation",
          "x_gap": 1.8894854187965393,
          "margin": 0.05
        }
      },
      "is_inverse_relation": true,
      "derived_from_relation": "left_of"
    },
    {
      "subject_id": "Drawer|+00.95|+00.83|-02.20",
      "subject_type": "Drawer",
      "relation": "right_of",
      "object_id": "WineBottle|-01.00|+01.65|-02.58",
      "object_type": "WineBottle",
      "relation_family": "geometric",
      "candidate_for_text": true,
      "verbalizable": true,
      "evidence": {
        "source": "inverse_relation",
        "forward_relation": "left_of",
        "forward_evidence": {
          "rule": "x_separation",
          "x_gap": 1.6671329736709595,
          "margin": 0.05
        }
      },
      "is_inverse_relation": true,
      "derived_from_relation": "left_of"
    },
    {
      "subject_id": "WineBottle|-01.00|+01.65|-02.58",
      "subject_type": "WineBottle",
      "relation": "left_of",
      "object_id": "Spoon|+00.98|+00.77|-02.29",
      "object_type": "Spoon",
      "relation_family": "geometric",
      "candidate_for_text": true,
      "verbalizable": true,
      "evidence": {
        "rule": "x_separation",
        "x_gap": 1.9196043014526367,
        "margin": 0.05
      }
    },
    {
      "subject_id": "WineBottle|-01.00|+01.65|-02.58",
      "subject_type": "WineBottle",
      "relation": "left_of",
      "object_id": "Drawer|+00.95|+00.56|-02.20",
      "object_type": "Drawer",
      "relation_family": "geometric",
      "candidate_for_text": true,
      "verbalizable": true,
      "evidence": {
        "rule": "x_separation",
        "x_gap": 1.6671329736709595,
        "margin": 0.05
      }
    },
    {
      "subject_id": "Drawer|+00.95|+00.22|-02.20",
      "subject_type": "Drawer",
      "relation": "right_of",
      "object_id": "WineBottle|-01.00|+01.65|-02.58",
      "object_type": "WineBottle",
      "relation_family": "geometric",
      "candidate_for_text": true,
      "verbalizable": true,
      "evidence": {
        "source": "inverse_relation",
        "forward_relation": "left_of",
        "forward_evidence": {
          "rule": "x_separation",
          "x_gap": 1.6671329736709595,
          "margin": 0.05
        }
      },
      "is_inverse_relation": true,
      "derived_from_relation": "left_of"
    },
    {
      "subject_id": "CounterTop|-01.87|+00.95|-01.21",
      "subject_type": "CounterTop",
      "relation": "below",
      "object_id": "WineBottle|-01.00|+01.65|-02.58",
      "object_type": "WineBottle",
      "relation_family": "geometric",
      "candidate_for_text": true,
      "verbalizable": true,
      "evidence": {
        "source": "inverse_relation",
        "forward_relation": "above",
        "forward_evidence": {
          "rule": "vertical_clearance_with_xz_overlap",
          "y_clearance": 0.7270983159542084,
          "x_overlap": 0.08820748329162598,
          "z_overlap": 0.08820009231567383,
          "y_margin": 0.03
        }
      },
      "is_inverse_relation": true,
      "derived_from_relation": "above"
    },
    {
      "subject_id": "WineBottle|-01.00|+01.65|-02.58",
      "subject_type": "WineBottle",
      "relation": "above",
      "object_id": "Cabinet|-01.18|+00.50|-02.20",
      "object_type": "Cabinet",
      "relation_family": "geometric",
      "candidate_for_text": true,
      "verbalizable": true,
      "evidence": {
        "rule": "vertical_clearance_with_xz_overlap",
        "y_clearance": 0.774998128414154,
        "x_overlap": 0.08820748329162598,
        "z_overlap": 0.06377196311950684,
        "y_margin": 0.03
      }
    },
    {
      "subject_id": "Cabinet|-01.69|+02.02|-02.46",
      "subject_type": "Cabinet",
      "relation": "left_of",
      "object_id": "Fork|+00.95|+00.77|-02.37",
      "object_type": "Fork",
      "relation_family": "geometric",
      "candidate_for_text": true,
      "verbalizable": true,
      "evidence": {
        "rule": "x_separation",
        "x_gap": 2.1507906317710876,
        "margin": 0.05
      }
    },
    {
      "subject_id": "Cabinet|-01.69|+02.02|-02.46",
      "subject_type": "Cabinet",
      "relation": "left_of",
      "object_id": "Spoon|+00.98|+00.77|-02.29",
      "object_type": "Spoon",
      "relation_family": "geometric",
      "candidate_for_text": true,
      "verbalizable": true,
      "evidence": {
        "rule": "x_separation",
        "x_gap": 2.180909514427185,
        "margin": 0.05
      }
    },
    {
      "subject_id": "Cabinet|-01.69|+02.02|-02.46",
      "subject_type": "Cabinet",
      "relation": "above",
      "object_id": "Pot|-01.22|+00.90|-02.36",
      "object_type": "Pot",
      "relation_family": "geometric",
      "candidate_for_text": true,
      "verbalizable": true,
      "evidence": {
        "rule": "vertical_clearance_with_xz_overlap",
        "y_clearance": 0.6234078407287598,
        "x_overlap": 0.13756239414215088,
        "z_overlap": 0.032553672790527344,
        "y_margin": 0.03
      }
    },
    {
      "subject_id": "WineBottle|-01.00|+01.65|-02.58",
      "subject_type": "WineBottle",
      "relation": "right_of",
      "object_id": "Cabinet|-01.69|+02.02|-02.46",
      "object_type": "Cabinet",
      "relation_family": "geometric",
      "candidate_for_text": true,
      "verbalizable": true,
      "evidence": {
        "source": "inverse_relation",
        "forward_relation": "left_of",
        "forward_evidence": {
          "rule": "x_separation",
          "x_gap": 0.17309772968292236,
          "margin": 0.05
        }
      },
      "is_inverse_relation": true,
      "derived_from_relation": "left_of"
    },
    {
      "subject_id": "Fork|+00.95|+00.77|-02.37",
      "subject_type": "Fork",
      "relation": "right_of",
      "object_id": "Cabinet|-01.55|+00.50|+00.38",
      "object_type": "Cabinet",
      "relation_family": "geometric",
      "candidate_for_text": true,
      "verbalizable": true,
      "evidence": {
        "source": "inverse_relation",
        "forward_relation": "left_of",
        "forward_evidence": {
          "rule": "x_separation",
          "x_gap": 2.464891016483307,
          "margin": 0.05
        }
      },
      "is_inverse_relation": true,
      "derived_from_relation": "left_of"
    },
    {
      "subject_id": "Cabinet|-01.55|+00.50|+00.38",
      "subject_type": "Cabinet",
      "relation": "left_of",
      "object_id": "Spoon|+00.98|+00.77|-02.29",
      "object_type": "Spoon",
      "relation_family": "geometric",
      "candidate_for_text": true,
      "verbalizable": true,
      "evidence": {
        "rule": "x_separation",
        "x_gap": 2.4950098991394043,
        "margin": 0.05
      }
    },
    {
      "subject_id": "Cabinet|-01.55|+00.50|+00.38",
      "subject_type": "Cabinet",
      "relation": "left_of",
      "object_id": "Pot|-01.22|+00.90|-02.36",
      "object_type": "Pot",
      "relation_family": "geometric",
      "candidate_for_text": true,
      "verbalizable": true,
      "evidence": {
        "rule": "x_separation",
        "x_gap": 0.17653799057006836,
        "margin": 0.05
      }
    },
    {
      "subject_id": "Cabinet|-01.55|+00.50|+00.38",
      "subject_type": "Cabinet",
      "relation": "left_of",
      "object_id": "WineBottle|-01.00|+01.65|-02.58",
      "object_type": "WineBottle",
      "relation_family": "geometric",
      "candidate_for_text": true,
      "verbalizable": true,
      "evidence": {
        "rule": "x_separation",
        "x_gap": 0.4871981143951416,
        "margin": 0.05
      }
    },
    {
      "subject_id": "Drawer|-01.56|+00.84|+00.20",
      "subject_type": "Drawer",
      "relation": "left_of",
      "object_id": "Fork|+00.95|+00.77|-02.37",
      "object_type": "Fork",
      "relation_family": "geometric",
      "candidate_for_text": true,
      "verbalizable": true,
      "evidence": {
        "rule": "x_separation",
        "x_gap": 2.470802128314972,
        "margin": 0.05
      }
    },
    {
      "subject_id": "Drawer|-01.56|+00.84|+00.20",
      "subject_type": "Drawer",
      "relation": "left_of",
      "object_id": "Spoon|+00.98|+00.77|-02.29",
      "object_type": "Spoon",
      "relation_family": "geometric",
      "candidate_for_text": true,
      "verbalizable": true,
      "evidence": {
        "rule": "x_separation",
        "x_gap": 2.5009210109710693,
        "margin": 0.05
      }
    },
    {
      "subject_id": "Pot|-01.22|+00.90|-02.36",
      "subject_type": "Pot",
      "relation": "right_of",
      "object_id": "Drawer|-01.56|+00.84|+00.20",
      "object_type": "Drawer",
      "relation_family": "geometric",
      "candidate_for_text": true,
      "verbalizable": true,
      "evidence": {
        "source": "inverse_relation",
        "forward_relation": "left_of",
        "forward_evidence": {
          "rule": "x_separation",
          "x_gap": 0.1824491024017334,
          "margin": 0.05
        }
      },
      "is_inverse_relation": true,
      "derived_from_relation": "left_of"
    },
    {
      "subject_id": "Drawer|-01.56|+00.84|+00.20",
      "subject_type": "Drawer",
      "relation": "left_of",
      "object_id": "WineBottle|-01.00|+01.65|-02.58",
      "object_type": "WineBottle",
      "relation_family": "geometric",
      "candidate_for_text": true,
      "verbalizable": true,
      "evidence": {
        "rule": "x_separation",
        "x_gap": 0.49310922622680664,
        "margin": 0.05
      }
    }
  ]
}